setup.py
nebri_client/__init__.py
nebri_client/nebri_client.py
python_nebri.egg-info/PKG-INFO
python_nebri.egg-info/SOURCES.txt
python_nebri.egg-info/dependency_links.txt
python_nebri.egg-info/requires.txt
python_nebri.egg-info/top_level.txt