Metadata-Version: 1.0
Name: python-nebri
Version: 0.1.5
Summary: python-nebri is a simple and easy-to-use package to make nebri api requests from a python application.
Home-page: http://github.com/briem-bixly/python-nebri/
Author: briem-bixly
Author-email: UNKNOWN
License: UNKNOWN
Platform: UNKNOWN
